jw_lensegua/__init__.py
jw_lensegua/tests/__init__.py
jw_lensegua/tests/test_solution.py
jw_lensegua/v1/cam.py
jw_lensegua/v1/lensegua.py
jw_lensegua/v1/results_model.py
jw_lensegua/v1/solutions.py
jw_lensegua/v2/model_class_tf.py
jw_lensegua/v2/model_kmean_tf2.py
jw_lensegua/v2/model_transfer.py
jw_lensegua/v2/sign_language.py
jw_lensegua-1.0.5.dist-info/LICENSE
jw_lensegua-1.0.5.dist-info/METADATA
jw_lensegua-1.0.5.dist-info/WHEEL
jw_lensegua-1.0.5.dist-info/top_level.txt
jw_lensegua-1.0.5.dist-info/RECORD
