Metadata-Version: 2.1
Name: jw_lensegua
Version: 1.0.5
Summary: Paquete para administracion de la informacion de datos para reconocer señales, utilizado para LENSEGUA - lenguaje de señas de Guatemala - (model-2)
Author-email: Jose Orlando Wannan Escobar <jwannan13@gmail.com>
Project-URL: Homepage, https://github.com/JoWan1998/lenguaje_senas
Project-URL: Bug Tracker, https://github.com/JoWan1998/lenguaje_senas/issues
Classifier: Programming Language :: Python :: 3
Classifier: License :: OSI Approved :: MIT License
Classifier: Operating System :: OS Independent
Requires-Python: >=3.7
License-File: LICENSE
